src/demo.py
src/exception.py
src/spreadsheet.py
wework_sheet-0.1.0.dist-info/WHEEL
wework_sheet-0.1.0.dist-info/METADATA
wework_sheet-0.1.0.dist-info/RECORD
