Metadata-Version: 2.1
Name: wework-sheet
Version: 0.1.0
Summary: 
Author: wn
Author-email: 320753691@qq.com
Requires-Python: >=3.10,<4.0
Classifier: Programming Language :: Python :: 3
Classifier: Programming Language :: Python :: 3.10
Classifier: Programming Language :: Python :: 3.11
Requires-Dist: requests (>=2.28.2,<3.0.0)
